<?xml version="1.0" encoding="UTF-8"?>
<comment version="3.0">
  <caption>Online webinar. E-learning, training podcast concept with video lector man, business coaching.</caption>
  <note>Online webinar. E-learning, training podcast concept. Vector illustration with video lector man, business coaching.</note>
  <place/>
  <categories>
    <category value="online"/>
    <category value="webinar"/>
    <category value="internet"/>
    <category value="training"/>
    <category value="digital"/>
    <category value="concept"/>
    <category value="education"/>
    <category value="virtual"/>
    <category value="vector"/>
    <category value="flat"/>
    <category value="illustration"/>
    <category value="web"/>
    <category value="video"/>
    <category value="communication"/>
    <category value="technology"/>
    <category value="distance"/>
    <category value="study"/>
    <category value="home"/>
    <category value="teaching"/>
    <category value="network"/>
    <category value="information"/>
    <category value="teacher"/>
    <category value="student"/>
    <category value="people"/>
    <category value="computer"/>
    <category value="book"/>
    <category value="university"/>
    <category value="conference"/>
    <category value="character"/>
    <category value="screen"/>
    <category value="design"/>
    <category value="website"/>
    <category value="class"/>
    <category value="idea"/>
    <category value="media"/>
    <category value="man"/>
    <category value="icon"/>
    <category value="presentation"/>
    <category value="creative"/>
    <category value="college"/>
    <category value="e-learning"/>
    <category value="work"/>
    <category value="graphic"/>
    <category value="social"/>
    <category value="symbol"/>
    <category value="workshop"/>
    <category value="document"/>
    <category value="electronic"/>
    <category value="story"/>
  </categories>
</comment>
